utils_twitter/Tweet.py
utils_twitter/Twitter.py
utils_twitter/TwitterActionerMixin.py
utils_twitter/TwitterActionerMixinHelpers.py
utils_twitter/TwitterBase.py
utils_twitter/TwitterLoaderMixin.py
utils_twitter/__init__.py
utils_twitter_nuuuwan-1.0.1.dist-info/LICENSE
utils_twitter_nuuuwan-1.0.1.dist-info/METADATA
utils_twitter_nuuuwan-1.0.1.dist-info/WHEEL
utils_twitter_nuuuwan-1.0.1.dist-info/top_level.txt
utils_twitter_nuuuwan-1.0.1.dist-info/RECORD
