Metadata-Version: 2.1
Name: utils_twitter-nuuuwan
Version: 1.0.1
Summary: Utilities for Twitter
Home-page: https://github.com/nuuuwan/utils_twitter
Author: Nuwan I. Senaratna
Author-email: nuuuwan@gmail.com
Project-URL: Bug Tracker, https://github.com/nuuuwan/utils_twitter/issues
Classifier: Programming Language :: Python :: 3
Classifier: License :: OSI Approved :: MIT License
Classifier: Operating System :: OS Independent
Requires-Python: >=3.10
License-File: LICENSE
Requires-Dist: tweepy
Requires-Dist: utils-base-nuuuwan
